koncile_sdk/__init__.py
koncile_sdk/client.py
koncile_sdk/exceptions.py
koncile_sdk/versions.py
koncile_sdk/clients/auth.py
koncile_sdk/clients/base.py
koncile_sdk/clients/documents.py
koncile_sdk/clients/fields.py
koncile_sdk/clients/files.py
koncile_sdk/clients/folders.py
koncile_sdk/clients/instructions.py
koncile_sdk/clients/tasks.py
koncile_sdk/clients/templates.py
koncile-0.1.0.dist-info/LICENSE
koncile-0.1.0.dist-info/METADATA
koncile-0.1.0.dist-info/WHEEL
koncile-0.1.0.dist-info/top_level.txt
koncile-0.1.0.dist-info/RECORD
