Metadata-Version: 2.2
Name: koncile
Version: 0.1.0
Summary: Official Python SDK for Koncile API
Home-page: https://github.com/Koncile/koncile-python
Author: Koncile
Author-email: Koncile <support@koncile.ai>
License:                                  Apache License
Project-URL: Homepage, https://github.com/Koncile/koncile-python
Project-URL: Documentation, https://docs.koncile.ai
Project-URL: Repository, https://github.com/Koncile/koncile-python
Project-URL: Issue Tracker, https://github.com/Koncile/koncile-python/issues
Keywords: koncile,sdk,api,document,processing
Classifier: Development Status :: 4 - Beta
Classifier: Intended Audience :: Developers
Classifier: License :: OSI Approved :: Apache Software License
Classifier: Operating System :: OS Independent
Classifier: Programming Language :: Python :: 3
Classifier: Programming Language :: Python :: 3.10
Classifier: Programming Language :: Python :: 3.11
Requires-Python: >=3.10
License-File: LICENSE
Requires-Dist: requests>=2.25.0
Dynamic: author
Dynamic: home-page
Dynamic: requires-python
